jenkspy-0.4.1.dist-info/WHEEL
jenkspy-0.4.1.dist-info/LICENSE
jenkspy-0.4.1.dist-info/top_level.txt
jenkspy-0.4.1.dist-info/RECORD
jenkspy-0.4.1.dist-info/METADATA
jenkspy/__init__.py
jenkspy/jenks.cpython-310-x86_64-linux-gnu.so
jenkspy/core.py
jenkspy/src/jenks.c
jenkspy/src/jenks.pyx
jenkspy/src/_jenks.c
