Metadata-Version: 2.1
Name: jenkspy
Version: 0.4.1
Summary: Compute Natural Breaks (Fisher-Jenks algorithm)
Author-email: Matthieu Viry <matthieu.viry@cnrs.fr>
Maintainer-email: Matthieu Viry <matthieu.viry@cnrs.fr>
License: MIT License
Project-URL: Homepage, https://github.com/mthh/jenkspy
Project-URL: Repository, https://github.com/mthh/jenkspy.git
Project-URL: Issues, https://github.com/mthh/jenkspy/issues
Project-URL: Changelog, https://github.com/mthh/jenkspy/blob/master/CHANGES.rst
Classifier: Programming Language :: Python
Classifier: Development Status :: 5 - Production/Stable
Classifier: Operating System :: OS Independent
Classifier: License :: OSI Approved :: MIT License
Classifier: Programming Language :: Python :: 3.7
Classifier: Programming Language :: Python :: 3.8
Classifier: Programming Language :: Python :: 3.9
Classifier: Programming Language :: Python :: 3.10
Classifier: Programming Language :: Python :: 3.11
Classifier: Programming Language :: Python :: 3.12
Classifier: Topic :: Scientific/Engineering
Classifier: Typing :: Typed
Requires-Python: >=3.7
License-File: LICENSE
Requires-Dist: numpy
